fuel_pdsh-1.0.0.dev21.dist-info/DESCRIPTION.rst
fuel_pdsh-1.0.0.dev21.dist-info/METADATA
fuel_pdsh-1.0.0.dev21.dist-info/RECORD
fuel_pdsh-1.0.0.dev21.dist-info/WHEEL
fuel_pdsh-1.0.0.dev21.dist-info/entry_points.txt
fuel_pdsh-1.0.0.dev21.dist-info/metadata.json
fuel_pdsh-1.0.0.dev21.dist-info/pbr.json
fuel_pdsh-1.0.0.dev21.dist-info/top_level.txt
fuelpdsh/__init__.py
fuelpdsh/cli.py
fuelpdsh/cp.py
fuelpdsh/pdsh.py
fuelpdsh/ssh.py
fuelpdsh/stream.py
fuelpdsh/utils.py
