Metadata-Version: 2.0
Name: fuel-pdsh
Version: 1.0.0.dev21
Summary: Simple pure Python alternative to PDSH for OpenStack Fuel node.
Home-page: https://github.com/9seconds/fuel-pdsh
Author: Sergey Arkhipov
Author-email: serge@aerialsounds.org
License: MIT
Platform: UNKNOWN
Classifier: Environment :: OpenStack
Classifier: Intended Audience :: Information Technology
Classifier: Intended Audience :: System Administrators
Classifier: Operating System :: POSIX :: Linux
Classifier: Programming Language :: Python
Classifier: Programming Language :: Python :: 2
Classifier: Programming Language :: Python :: 2.6
Classifier: Programming Language :: Python :: 2.7
Classifier: Programming Language :: Python :: 3
Classifier: Programming Language :: Python :: 3.4
Requires-Dist: futures
Requires-Dist: pycrypto (<2.5)
Requires-Dist: python-fuelclient (>=7.0.0)
Requires-Dist: spur (<=0.4)
